adafruit_lsm303_accel.py
adafruit_circuitpython_lsm303_accel-1.1.26.dist-info/licenses/LICENSE
adafruit_circuitpython_lsm303_accel-1.1.26.dist-info/METADATA
adafruit_circuitpython_lsm303_accel-1.1.26.dist-info/WHEEL
adafruit_circuitpython_lsm303_accel-1.1.26.dist-info/top_level.txt
adafruit_circuitpython_lsm303_accel-1.1.26.dist-info/RECORD
